blackcap/__init__.py
blackcap/alembic.ini
blackcap/auther/__init__.py
blackcap/auther/base.py
blackcap/auther/cookie_auther.py
blackcap/auther/registry.py
blackcap/blocs/__init__.py
blackcap/blocs/cluster.py
blackcap/blocs/job.py
blackcap/blocs/schedule.py
blackcap/blocs/schedule_update.py
blackcap/blocs/user.py
blackcap/cli/__init__.py
blackcap/cli/create.py
blackcap/cli/db.py
blackcap/cli/get.py
blackcap/cli/main.py
blackcap/cli/publish.py
blackcap/cli/schedule.py
blackcap/cli/subscribe.py
blackcap/cluster/__init__.py
blackcap/cluster/base.py
blackcap/cluster/registry.py
blackcap/cluster/slurm_cluster.py
blackcap/configs/__init__.py
blackcap/configs/base.py
blackcap/configs/default.py
blackcap/configs/registry.py
blackcap/configs/testing.py
blackcap/db.py
blackcap/flow/__init__.py
blackcap/flow/executor.py
blackcap/flow/flow.py
blackcap/flow/step.py
blackcap/messenger/__init__.py
blackcap/messenger/base.py
blackcap/messenger/gcp_messenger.py
blackcap/messenger/nats_messenger.py
blackcap/messenger/registry.py
blackcap/migrations/README
blackcap/migrations/env.py
blackcap/migrations/script.py.mako
blackcap/models/__init__.py
blackcap/models/cluster.py
blackcap/models/job.py
blackcap/models/meta/__init__.py
blackcap/models/meta/helpers.py
blackcap/models/meta/mixins.py
blackcap/models/meta/orm.py
blackcap/models/protagonist.py
blackcap/models/schedule.py
blackcap/observer/__init__.py
blackcap/observer/base.py
blackcap/observer/elastic_observer.py
blackcap/observer/registry.py
blackcap/routes/__init__.py
blackcap/routes/cluster/__init__.py
blackcap/routes/cluster/get.py
blackcap/routes/cluster/post.py
blackcap/routes/job/__init__.py
blackcap/routes/job/get.py
blackcap/routes/job/post.py
blackcap/routes/schedule/__init__.py
blackcap/routes/schedule/get.py
blackcap/routes/schedule/post.py
blackcap/routes/status.py
blackcap/routes/user/__init__.py
blackcap/routes/user/get.py
blackcap/routes/user/post.py
blackcap/scheduler/__init__.py
blackcap/scheduler/base.py
blackcap-0.41.0.dist-info/entry_points.txt
blackcap-0.41.0.dist-info/WHEEL
blackcap-0.41.0.dist-info/METADATA
blackcap-0.41.0.dist-info/RECORD
